beekeeper/llms/watsonx/__init__.py
beekeeper/llms/watsonx/base.py
beekeeper/llms/watsonx/supporting_classes/__init__.py
beekeeper/llms/watsonx/supporting_classes/enums.py
beekeeper_llms_watsonx-1.0.0.dist-info/METADATA
beekeeper_llms_watsonx-1.0.0.dist-info/WHEEL
beekeeper_llms_watsonx-1.0.0.dist-info/RECORD
